tests/__init__.py
tests/test_geocoder.py
usgeocoder/__init__.py
usgeocoder/census_api.py
usgeocoder/geocoder.py
usgeocoder/utils.py
usgeocoder-0.2.dist-info/LICENSE
usgeocoder-0.2.dist-info/METADATA
usgeocoder-0.2.dist-info/WHEEL
usgeocoder-0.2.dist-info/top_level.txt
usgeocoder-0.2.dist-info/RECORD
