Metadata-Version: 2.1
Name: usgeocoder
Version: 0.2
Summary: USGeoCoder is an easy and free-to-use package for geocoding US addresses with the US Census Geocoder API
Home-page: https://github.com/ClayGendron/usgeocoder
Author: Clay Gendron
Author-email: chg@claygendron.io
Project-URL: Source Code, https://github.com/ClayGendron/usgeocoder/
Project-URL: Documentation, https://github.com/ClayGendron/usgeocoder/
Keywords: geocoding,geocoder,geospatial,US,census,api,address,coordinates,batch processing
Classifier: Intended Audience :: Developers
Classifier: Topic :: Software Development :: Libraries
Classifier: Topic :: Utilities
Classifier: License :: OSI Approved :: MIT License
Classifier: Programming Language :: Python :: 3
Classifier: Programming Language :: Python :: 3.8
Classifier: Programming Language :: Python :: 3.9
Classifier: Programming Language :: Python :: 3.10
License-File: LICENSE
Requires-Dist: pandas ~=2.1.0
Requires-Dist: requests ~=2.31.0
